qitesse-0.0.3.dist-info/METADATA
qitesse-0.0.3.dist-info/WHEEL
qitesse-0.0.3.dist-info/licenses/LICENSE
qitesse/__init__.py
qitesse/qitesse.cpython-313-x86_64-linux-gnu.so
qitesse-0.0.3.dist-info/RECORD
