Metadata-Version: 2.4
Name: qitesse
Version: 0.0.3
Classifier: Programming Language :: Python :: 3
Classifier: License :: OSI Approved :: MIT License
Classifier: Operating System :: OS Independent
Classifier: Development Status :: 3 - Alpha
Classifier: Topic :: Scientific/Engineering :: Artificial Intelligence
License-File: LICENSE
Summary: qitesse: performant quantum circuit simulation in Python
Author-email: Osama Elmahdy <you@example.com>
License: MIT
Requires-Python: >=3.8
